widget_state/__init__.py
widget_state/basic_state.py
widget_state/dict_state.py
widget_state/higher_order_state.py
widget_state/list_state.py
widget_state/py.typed
widget_state/state.py
widget_state/types.py
widget_state/util.py
widget_state-0.0.7.dist-info/METADATA
widget_state-0.0.7.dist-info/WHEEL
widget_state-0.0.7.dist-info/licenses/LICENSE
widget_state-0.0.7.dist-info/RECORD
