Metadata-Version: 2.4
Name: widget_state
Version: 0.0.7
Summary: Reactive wrapping around values for GUI applications
Project-URL: Homepage, https://github.com/pLeminoq/widget_state
Author-email: Tamino Huxohl <thuxohl@mailbox.org>
License-File: LICENSE
Classifier: License :: OSI Approved :: MIT License
Classifier: Operating System :: OS Independent
Classifier: Programming Language :: Python :: 3
Requires-Python: >=3.10
